{
  "clientId": "mobility-hq",
  "clientName": "Mobility HQ",
  "current7d": {
    "clicks": 0,
    "impressions": 0,
    "costMicros": 0,
    "conversions": 0,
    "conversionValue": 0,
    "ctr": 0,
    "averageCpc": 0
  },
  "prev7d": {
    "clicks": 0,
    "impressions": 0,
    "costMicros": 0,
    "conversions": 0,
    "conversionValue": 0,
    "ctr": 0,
    "averageCpc": 0
  },
  "current30d": {
    "clicks": 0,
    "impressions": 0,
    "costMicros": 0,
    "conversions": 0,
    "conversionValue": 0,
    "ctr": 0,
    "averageCpc": 0
  },
  "prev30d": {
    "clicks": 0,
    "impressions": 0,
    "costMicros": 0,
    "conversions": 0,
    "conversionValue": 0,
    "ctr": 0,
    "averageCpc": 0
  },
  "yoy30d": {
    "clicks": 18593,
    "impressions": 751079,
    "costMicros": 18384579199,
    "conversions": 104.733233,
    "conversionValue": 50356.521634474,
    "ctr": 0.024755052397950148,
    "averageCpc": 988850.64
  },
  "lastUpdated": "2026-03-09T00:00:00.000Z"
}
