[{"url":"https://offshoring.satelliteoffice.com.au/book-a-call/","clicks":287,"impressions":9670,"costMicros":12235489599,"conversions":4.0,"ctr":0.0296794208893485,"averageCpc":42632368},{"url":"https://www.satelliteoffice.com.au/","clicks":182,"impressions":9094,"costMicros":8851817576,"conversions":0.0,"ctr":0.0200131955135254,"averageCpc":48636360},{"url":"https://offshoring.satelliteoffice.com/free-consultation/","clicks":68,"impressions":3432,"costMicros":1771772176,"conversions":0.0,"ctr":0.019813519813519812,"averageCpc":26055473},{"url":"https://offshoring.satelliteoffice.com/","clicks":56,"impressions":6375,"costMicros":1500461397,"conversions":0.0,"ctr":0.008784313725490196,"averageCpc":26793954},{"url":"https://www.satelliteoffice.com/services/talent-recruitment/","clicks":6,"impressions":6947,"costMicros":274740000,"conversions":0.0,"ctr":0.0008636821649632935,"averageCpc":45790000},{"url":"https://www.satelliteoffice.com/services/","clicks":5,"impressions":5996,"costMicros":210510000,"conversions":0.0,"ctr":0.0008338892595063375,"averageCpc":42102000},{"url":"https://www.satelliteoffice.com/","clicks":2,"impressions":3791,"costMicros":92510000,"conversions":0.0,"ctr":0.0005275652862041678,"averageCpc":46255000},{"url":"https://www.satelliteoffice.com/resources-hub/#case-studies","clicks":0,"impressions":3549,"costMicros":0,"conversions":0.0,"ctr":0.0,"averageCpc":0}]
