{
  "clientId": "aif",
  "clientName": "Australian Institute of Fitness",
  "current7d": { "clicks": 848, "impressions": 12888, "costMicros": 13506460323, "conversions": 129.5, "ctr": 0.06579764121663563, "averageCpc": 15927429.626179244 },
  "prev7d": { "clicks": 944, "impressions": 14207, "costMicros": 15812243460, "conversions": 147.5, "ctr": 0.06644611811079046, "averageCpc": 16750257.902542373 },
  "current30d": { "clicks": 3436, "impressions": 50019, "costMicros": 58408288642, "conversions": 530.983906, "ctr": 0.06869389631939862, "averageCpc": 16998919.86088475 },
  "prev30d": { "clicks": 357, "impressions": 5623, "costMicros": 8042973518, "conversions": 66.016094, "ctr": 0.06348924061888672, "averageCpc": 22529337.585434172 },
  "yoy30d": { "clicks": 3015, "impressions": 48829, "costMicros": 38616678830, "conversions": 362, "ctr": 0.0617460935100043, "averageCpc": 12808185.349917082 },
  "lastUpdated": "2026-03-09T00:00:00.000Z"
}
