[
  {
    "keyword": "jay abraham",
    "matchType": "EXACT",
    "campaign": "Jay Abraham Mastermind",
    "adGroup": "Jay Abraham branded",
    "clicks": 0,
    "impressions": 0,
    "costMicros": 0,
    "conversions": 0,
    "averageCpc": null,
    "searchImpressionShare": null
  },
  {
    "keyword": "jay abraham seminar",
    "matchType": "EXACT",
    "campaign": "Jay Abraham Mastermind",
    "adGroup": "Jay Abraham branded",
    "clicks": 0,
    "impressions": 0,
    "costMicros": 0,
    "conversions": 0,
    "averageCpc": null,
    "searchImpressionShare": null
  },
  {
    "keyword": "jay abraham marketing",
    "matchType": "EXACT",
    "campaign": "Jay Abraham Mastermind",
    "adGroup": "Jay Abraham branded",
    "clicks": 0,
    "impressions": 0,
    "costMicros": 0,
    "conversions": 0,
    "averageCpc": null,
    "searchImpressionShare": null
  },
  {
    "keyword": "jay abraham coaching",
    "matchType": "EXACT",
    "campaign": "Jay Abraham Mastermind",
    "adGroup": "Jay Abraham branded",
    "clicks": 0,
    "impressions": 0,
    "costMicros": 0,
    "conversions": 0,
    "averageCpc": null,
    "searchImpressionShare": null
  },
  {
    "keyword": "jay abraham consulting",
    "matchType": "EXACT",
    "campaign": "Jay Abraham Mastermind",
    "adGroup": "Jay Abraham branded",
    "clicks": 0,
    "impressions": 0,
    "costMicros": 0,
    "conversions": 0,
    "averageCpc": null,
    "searchImpressionShare": null
  },
  {
    "keyword": "jay abraham business coaching",
    "matchType": "PHRASE",
    "campaign": "TG - BATB",
    "adGroup": "Ad group 1",
    "clicks": 0,
    "impressions": 0,
    "costMicros": 0,
    "conversions": 0,
    "averageCpc": null,
    "searchImpressionShare": null
  },
  {
    "keyword": "best business coach",
    "matchType": "PHRASE",
    "campaign": "TG - BATB",
    "adGroup": "Ad group 1",
    "clicks": 0,
    "impressions": 0,
    "costMicros": 0,
    "conversions": 0,
    "averageCpc": null,
    "searchImpressionShare": null
  },
  {
    "keyword": "business coaching services",
    "matchType": "PHRASE",
    "campaign": "TG - BATB",
    "adGroup": "Ad group 1",
    "clicks": 0,
    "impressions": 0,
    "costMicros": 0,
    "conversions": 0,
    "averageCpc": null,
    "searchImpressionShare": null
  },
  {
    "keyword": "top business coaches",
    "matchType": "PHRASE",
    "campaign": "TG - BATB",
    "adGroup": "Ad group 1",
    "clicks": 0,
    "impressions": 0,
    "costMicros": 0,
    "conversions": 0,
    "averageCpc": null,
    "searchImpressionShare": null
  },
  {
    "keyword": "business mastery seminar",
    "matchType": "PHRASE",
    "campaign": "TG - BATB",
    "adGroup": "Ad group 1",
    "clicks": 0,
    "impressions": 0,
    "costMicros": 0,
    "conversions": 0,
    "averageCpc": null,
    "searchImpressionShare": null
  },
  {
    "keyword": "jay abraham",
    "matchType": "EXACT",
    "campaign": "Branded Search",
    "adGroup": "Jay Abraham",
    "clicks": 0,
    "impressions": 0,
    "costMicros": 0,
    "conversions": 0,
    "averageCpc": null,
    "searchImpressionShare": null
  },
  {
    "keyword": "jay abraham strategy",
    "matchType": "EXACT",
    "campaign": "Branded Search",
    "adGroup": "Jay Abraham",
    "clicks": 0,
    "impressions": 0,
    "costMicros": 0,
    "conversions": 0,
    "averageCpc": null,
    "searchImpressionShare": null
  },
  {
    "keyword": "jay abraham marketing",
    "matchType": "EXACT",
    "campaign": "Branded Search",
    "adGroup": "Jay Abraham",
    "clicks": 0,
    "impressions": 0,
    "costMicros": 0,
    "conversions": 0,
    "averageCpc": null,
    "searchImpressionShare": null
  },
  {
    "keyword": "jay abraham preeminence",
    "matchType": "EXACT",
    "campaign": "Branded Search",
    "adGroup": "Jay Abraham",
    "clicks": 0,
    "impressions": 0,
    "costMicros": 0,
    "conversions": 0,
    "averageCpc": null,
    "searchImpressionShare": null
  }
]
