[
  {"keyword":"government bonds interest rates","matchType":"BROAD","campaign":"WP - Government Bonds - QLD","adGroup":"Government Bond Rates","clicks":760,"impressions":9708,"costMicros":3215600718,"conversions":29.016749,"averageCpc":4231053.5763157895,"searchImpressionShare":0.12125902202062613},
  {"keyword":"fixed income","matchType":"BROAD","campaign":"WP - Fixed Income/Investments - E + P","adGroup":"Fixed Income (Generic)","clicks":344,"impressions":12020,"costMicros":2569886664,"conversions":21,"averageCpc":7470600.76744186,"searchImpressionShare":0.0999},
  {"keyword":"government bonds australia","matchType":"PHRASE","campaign":"WP - Government Bonds - E + P + B","adGroup":"Australian Government Bonds","clicks":469,"impressions":3037,"costMicros":1654684623,"conversions":24.5,"averageCpc":3528112.2025586353,"searchImpressionShare":0.22018348623853212},
  {"keyword":"fixed income","matchType":"PHRASE","campaign":"WP - Fixed Income/Investments - QLD","adGroup":"Fixed Income (Generic)","clicks":125,"impressions":1261,"costMicros":1380628845,"conversions":7,"averageCpc":11045030.76,"searchImpressionShare":0.426679744973026},
  {"keyword":"fiig securities","matchType":"EXACT","campaign":"WP - Brand","adGroup":"FIIG Securities Branded","clicks":242,"impressions":1592,"costMicros":923021922,"conversions":18.507621,"averageCpc":3814140.173553719,"searchImpressionShare":0.7571552471812663},
  {"keyword":"government bonds australia","matchType":"EXACT","campaign":"WP - Government Bonds - E + P + B","adGroup":"Australian Government Bonds","clicks":241,"impressions":1599,"costMicros":784300531,"conversions":5,"averageCpc":3254359.049792531,"searchImpressionShare":0.0999},
  {"keyword":"investing in government bonds australia","matchType":"EXACT","campaign":"WP - Government Bonds - E + P + B","adGroup":"Australian Government Bonds","clicks":187,"impressions":1870,"costMicros":761179358,"conversions":18,"averageCpc":4070477.8502673795,"searchImpressionShare":0.1593084586833366},
  {"keyword":"investment in australia","matchType":"PHRASE","campaign":"WP - Fixed Income/Investments - E + P","adGroup":"Fixed Income (Generic)","clicks":90,"impressions":2024,"costMicros":726985972,"conversions":3.5,"averageCpc":8077621.911111111,"searchImpressionShare":0.0999},
  {"keyword":"fiig","matchType":"EXACT","campaign":"WP - Brand","adGroup":"FIIG Securities Branded","clicks":176,"impressions":1118,"costMicros":652921156,"conversions":8,"averageCpc":3709779.2954545454,"searchImpressionShare":0.7256438969764838},
  {"keyword":"government bond","matchType":"PHRASE","campaign":"WP - Government Bonds - E + P + B","adGroup":"Government Bonds (Generic)","clicks":148,"impressions":1054,"costMicros":580136469,"conversions":8.666666,"averageCpc":3919841.006756757,"searchImpressionShare":0.1976651631732555},
  {"keyword":"fiig","matchType":"PHRASE","campaign":"WP - Brand","adGroup":"FIIG Securities Branded","clicks":124,"impressions":762,"costMicros":534938309,"conversions":10,"averageCpc":4314018.620967742,"searchImpressionShare":0.4405850091407678},
  {"keyword":"invest in bonds","matchType":"PHRASE","campaign":"WP - All Non-Government Bonds - High Intent","adGroup":"Generic Bonds","clicks":111,"impressions":1455,"costMicros":529523456,"conversions":4.833334,"averageCpc":4770481.585585586,"searchImpressionShare":0.1419982090315978},
  {"keyword":"investment accounts","matchType":"PHRASE","campaign":"WP - Fixed Income/Investments - E + P","adGroup":"Fixed Income (Generic)","clicks":89,"impressions":1117,"costMicros":526133489,"conversions":7,"averageCpc":5911612.235955056,"searchImpressionShare":0.0999},
  {"keyword":"government bond","matchType":"EXACT","campaign":"WP - Government Bonds - E + P + B","adGroup":"Government Bonds (Generic)","clicks":140,"impressions":1267,"costMicros":503306802,"conversions":6.5,"averageCpc":3595048.5857142857,"searchImpressionShare":0.17232890201870998},
  {"keyword":"how do i buy government bonds in australia","matchType":"EXACT","campaign":"WP - Government Bonds - E + P + B","adGroup":"Australian Government Bonds","clicks":132,"impressions":760,"costMicros":500501919,"conversions":5,"averageCpc":3791681.2045454546,"searchImpressionShare":0.5793901156677181},
  {"keyword":"fixed income bonds","matchType":"PHRASE","campaign":"WP - Fixed Income/Investments - QLD","adGroup":"Fixed Income (Generic)","clicks":49,"impressions":448,"costMicros":495490770,"conversions":4,"averageCpc":10112056.530612245,"searchImpressionShare":0.40700808625336926},
  {"keyword":"government bonds australia","matchType":"PHRASE","campaign":"WP - Government Bonds - QLD","adGroup":"Australian Government Bonds","clicks":97,"impressions":630,"costMicros":425463530,"conversions":8.011164,"averageCpc":4386221.958762887,"searchImpressionShare":0.2560840707964602},
  {"keyword":"investing in government bonds","matchType":"PHRASE","campaign":"WP - Government Bonds - E + P + B","adGroup":"Government Bonds (Generic)","clicks":112,"impressions":848,"costMicros":418779389,"conversions":4,"averageCpc":3739101.6875,"searchImpressionShare":0.23211314475873543},
  {"keyword":"investment advice","matchType":"PHRASE","campaign":"WP - Fixed Income/Investments - E + P","adGroup":"Fixed Income (Generic)","clicks":49,"impressions":1297,"costMicros":333989929,"conversions":0,"averageCpc":6816121,"searchImpressionShare":0.0999},
  {"keyword":"retirement funds","matchType":"PHRASE","campaign":"WP - Retirement","adGroup":"Retirement Funds","clicks":60,"impressions":1336,"costMicros":321670707,"conversions":1,"averageCpc":5361178.45,"searchImpressionShare":0.1206577119036591},
  {"keyword":"retirement investment options","matchType":"PHRASE","campaign":"WP - Retirement","adGroup":"Retirement Informational","clicks":41,"impressions":909,"costMicros":261532033,"conversions":2,"averageCpc":6378830.073170732,"searchImpressionShare":0.17062203347489382},
  {"keyword":"government investments","matchType":"EXACT","campaign":"WP - Government Bonds - E + P + B","adGroup":"Government Bonds (Generic)","clicks":23,"impressions":864,"costMicros":256600283,"conversions":1,"averageCpc":11156534.043478262,"searchImpressionShare":0.10815239655878738},
  {"keyword":"best government bonds australia","matchType":"EXACT","campaign":"WP - Government Bonds - E + P + B","adGroup":"Australian Government Bonds","clicks":61,"impressions":428,"costMicros":248005901,"conversions":2,"averageCpc":4065670.5081967213,"searchImpressionShare":0.39135959339263027},
  {"keyword":"investment bonds australia","matchType":"EXACT","campaign":"WP - All Non-Government Bonds - High Intent","adGroup":"Australian Bonds","clicks":47,"impressions":435,"costMicros":233009471,"conversions":7,"averageCpc":4957648.319148936,"searchImpressionShare":0.1718229414564493},
  {"keyword":"corporate bonds","matchType":"PHRASE","campaign":"WP - All Non-Government Bonds - High Intent","adGroup":"Corporate Bonds","clicks":46,"impressions":422,"costMicros":209077854,"conversions":4.5,"averageCpc":4545170.739130435,"searchImpressionShare":0.21677852348993287},
  {"keyword":"invest in bonds","matchType":"EXACT","campaign":"WP - All Non-Government Bonds - High Intent","adGroup":"Generic Bonds","clicks":29,"impressions":608,"costMicros":206950911,"conversions":0,"averageCpc":7136238.310344827,"searchImpressionShare":0.0999},
  {"keyword":"buy australian government bonds","matchType":"EXACT","campaign":"WP - Government Bonds - E + P + B","adGroup":"Australian Government Bonds","clicks":46,"impressions":471,"costMicros":203511235,"conversions":2,"averageCpc":4424157.282608695,"searchImpressionShare":0.15064377682403435},
  {"keyword":"are australian government bonds a good investment","matchType":"PHRASE","campaign":"WP - Government Bonds - E + P + B","adGroup":"Australian Government Bonds","clicks":63,"impressions":450,"costMicros":201581872,"conversions":2,"averageCpc":3199712.253968254,"searchImpressionShare":0.12775842044134728},
  {"keyword":"australia bond","matchType":"PHRASE","campaign":"WP - All Non-Government Bonds - High Intent","adGroup":"Australian Bonds","clicks":47,"impressions":467,"costMicros":195510255,"conversions":1,"averageCpc":4159792.659574468,"searchImpressionShare":0.1862030286034773},
  {"keyword":"interest investments","matchType":"PHRASE","campaign":"WP - Fixed Income/Investments - E + P","adGroup":"Fixed Income (Generic)","clicks":40,"impressions":538,"costMicros":184196886,"conversions":3,"averageCpc":4604922.15,"searchImpressionShare":0.0999},
  {"keyword":"buy bonds","matchType":"PHRASE","campaign":"WP - All Non-Government Bonds - High Intent","adGroup":"Generic Bonds","clicks":23,"impressions":221,"costMicros":175689267,"conversions":2,"averageCpc":7638663.782608695,"searchImpressionShare":0.2213225371120108},
  {"keyword":"bonds investment","matchType":"PHRASE","campaign":"WP - All Non-Government Bonds - High Intent","adGroup":"Generic Bonds","clicks":32,"impressions":371,"costMicros":167813392,"conversions":1,"averageCpc":5244168.5,"searchImpressionShare":0.15508615897720957},
  {"keyword":"how do i buy government bonds","matchType":"EXACT","campaign":"WP - Government Bonds - E + P + B","adGroup":"Government Bonds (Generic)","clicks":37,"impressions":312,"costMicros":163746356,"conversions":2.5,"averageCpc":4425577.189189189,"searchImpressionShare":0.17651195499296765},
  {"keyword":"how to invest in australian government bonds","matchType":"PHRASE","campaign":"WP - Government Bonds - E + P + B","adGroup":"Australian Government Bonds","clicks":31,"impressions":310,"costMicros":158522567,"conversions":1,"averageCpc":5113631.193548387,"searchImpressionShare":0.35564053537284895},
  {"keyword":"fixed income investments","matchType":"EXACT","campaign":"WP - Fixed Income/Investments - QLD","adGroup":"Fixed Income (Generic)","clicks":11,"impressions":72,"costMicros":153961919,"conversions":1,"averageCpc":13996538.090909092,"searchImpressionShare":0.7833333333333333},
  {"keyword":"bond investing","matchType":"EXACT","campaign":"WP - All Non-Government Bonds - High Intent","adGroup":"Generic Bonds","clicks":21,"impressions":780,"costMicros":141289181,"conversions":3,"averageCpc":6728056.238095238,"searchImpressionShare":0.0999},
  {"keyword":"fixed income","matchType":"PHRASE","campaign":"WP - Fixed Income/Investments - E + P","adGroup":"Fixed Income (Generic)","clicks":29,"impressions":540,"costMicros":138545860,"conversions":2,"averageCpc":4777443.448275862,"searchImpressionShare":0.13834126444595513},
  {"keyword":"investment portfolio strategy","matchType":"PHRASE","campaign":"WP - Fixed Income/Investments - E + P","adGroup":"Fixed Income (Generic)","clicks":23,"impressions":394,"costMicros":132677020,"conversions":0,"averageCpc":5768566.0869565215,"searchImpressionShare":0.0999},
  {"keyword":"investment guide australia","matchType":"PHRASE","campaign":"WP - Fixed Income/Investments - E + P","adGroup":"Fixed Income (Generic)","clicks":33,"impressions":575,"costMicros":117035804,"conversions":2,"averageCpc":3546539.515151515,"searchImpressionShare":0.0999},
  {"keyword":"government bonds australia","matchType":"EXACT","campaign":"WP - Government Bonds - QLD","adGroup":"Australian Government Bonds","clicks":29,"impressions":140,"costMicros":116894591,"conversions":4.919005,"averageCpc":4030847.9655172415,"searchImpressionShare":0.448},
  {"keyword":"government bonds australia rates","matchType":"EXACT","campaign":"WP - Government Bonds - E + P + B","adGroup":"Government Bond Rates","clicks":26,"impressions":239,"costMicros":115862110,"conversions":2,"averageCpc":4456235,"searchImpressionShare":0.1345427059712774},
  {"keyword":"australian bonds","matchType":"PHRASE","campaign":"WP - All Non-Government Bonds - High Intent","adGroup":"Australian Bonds","clicks":25,"impressions":164,"costMicros":113204598,"conversions":0,"averageCpc":4528183.92,"searchImpressionShare":0.19487179487179487},
  {"keyword":"bond market","matchType":"PHRASE","campaign":"WP - All Non-Government Bonds - High Intent","adGroup":"Generic Bonds","clicks":13,"impressions":168,"costMicros":109129961,"conversions":1,"averageCpc":8394612.384615384,"searchImpressionShare":0.0999},
  {"keyword":"bond markets in australia","matchType":"PHRASE","campaign":"WP - All Non-Government Bonds - High Intent","adGroup":"Australian Bonds","clicks":16,"impressions":120,"costMicros":108044185,"conversions":0,"averageCpc":6752761.5625,"searchImpressionShare":0.17338709677419356},
  {"keyword":"fiig bonds","matchType":"EXACT","campaign":"WP - Brand","adGroup":"FIIG Securities Branded","clicks":27,"impressions":88,"costMicros":107788315,"conversions":3,"averageCpc":3992159.814814815,"searchImpressionShare":0.9245283018867925},
  {"keyword":"good investment","matchType":"PHRASE","campaign":"WP - Fixed Income/Investments - E + P","adGroup":"Fixed Income (Generic)","clicks":17,"impressions":351,"costMicros":105831256,"conversions":2,"averageCpc":6225368,"searchImpressionShare":0.0999},
  {"keyword":"invest bonds australia","matchType":"EXACT","campaign":"WP - All Non-Government Bonds - High Intent","adGroup":"Australian Bonds","clicks":24,"impressions":255,"costMicros":103086189,"conversions":1,"averageCpc":4295257.875,"searchImpressionShare":0.0999},
  {"keyword":"government bonds interest rates","matchType":"PHRASE","campaign":"WP - Government Bonds - E + P + B","adGroup":"Government Bond Rates","clicks":36,"impressions":357,"costMicros":90864705,"conversions":0.034205,"averageCpc":2524019.5833333335,"searchImpressionShare":0.14285714285714285},
  {"keyword":"gov bonds australia","matchType":"EXACT","campaign":"WP - Government Bonds - E + P + B","adGroup":"Australian Government Bonds","clicks":29,"impressions":214,"costMicros":89236243,"conversions":1,"averageCpc":3077111.827586207,"searchImpressionShare":0.23127035830618892},
  {"keyword":"what are bonds in australia","matchType":"PHRASE","campaign":"WP - Government Bonds - E + P + B","adGroup":"Government Bond Rates","clicks":15,"impressions":186,"costMicros":82212831,"conversions":1,"averageCpc":5480855.4,"searchImpressionShare":0.24193548387096775},
  {"keyword":"treasury bonds australia","matchType":"EXACT","campaign":"WP - Government Bonds - E + P + B","adGroup":"Government Bonds (Generic)","clicks":25,"impressions":110,"costMicros":80408829,"conversions":0,"averageCpc":3216353.16,"searchImpressionShare":0.391304347826087},
  {"keyword":"australian bonds","matchType":"EXACT","campaign":"WP - All Non-Government Bonds - High Intent","adGroup":"Australian Bonds","clicks":30,"impressions":206,"costMicros":80176854,"conversions":1,"averageCpc":2672561.8,"searchImpressionShare":0.27147766323024053},
  {"keyword":"how to purchase australian government bonds","matchType":"EXACT","campaign":"WP - Government Bonds - E + P + B","adGroup":"Australian Government Bonds","clicks":31,"impressions":133,"costMicros":79228966,"conversions":1,"averageCpc":2555773.0967741935,"searchImpressionShare":0.15842839036755388},
  {"keyword":"how do government bonds work","matchType":"EXACT","campaign":"WP - Government Bonds - E + P + B","adGroup":"Government Bonds (Generic)","clicks":21,"impressions":354,"costMicros":77756215,"conversions":1,"averageCpc":3702676.904761905,"searchImpressionShare":0.11446921042689838},
  {"keyword":"aussie bonds","matchType":"EXACT","campaign":"WP - All Non-Government Bonds - High Intent","adGroup":"Australian Bonds","clicks":22,"impressions":151,"costMicros":76315325,"conversions":2,"averageCpc":3468878.409090909,"searchImpressionShare":0.10092449922958398},
  {"keyword":"investing in australian bonds","matchType":"EXACT","campaign":"WP - All Non-Government Bonds - High Intent","adGroup":"Australian Bonds","clicks":15,"impressions":118,"costMicros":73590206,"conversions":1,"averageCpc":4906013.733333333,"searchImpressionShare":0.13742690058479531},
  {"keyword":"fiig securities reviews","matchType":"EXACT","campaign":"WP - Brand","adGroup":"FIIG Securities Branded","clicks":6,"impressions":68,"costMicros":71715480,"conversions":0,"averageCpc":11952580,"searchImpressionShare":0.8},
  {"keyword":"corporate bonds","matchType":"EXACT","campaign":"WP - All Non-Government Bonds - High Intent","adGroup":"Corporate Bonds","clicks":16,"impressions":142,"costMicros":71134773,"conversions":0,"averageCpc":4445923.3125,"searchImpressionShare":0.222},
  {"keyword":"bonds investment","matchType":"PHRASE","campaign":"WP - Fixed Income/Investments - E + P","adGroup":"Fixed Income (Generic)","clicks":12,"impressions":213,"costMicros":67488833,"conversions":2,"averageCpc":5624069.416666667,"searchImpressionShare":0.1106687898089172},
  {"keyword":"where to buy government bonds","matchType":"EXACT","campaign":"WP - Government Bonds - E + P + B","adGroup":"Government Bond Rates","clicks":19,"impressions":278,"costMicros":67328553,"conversions":0,"averageCpc":3543608.052631579,"searchImpressionShare":0.0999},
  {"keyword":"government bond","matchType":"PHRASE","campaign":"WP - Government Bonds - QLD","adGroup":"Government Bonds (Generic)","clicks":15,"impressions":81,"costMicros":65545926,"conversions":1,"averageCpc":4369728.4,"searchImpressionShare":0.22653721682847897},
  {"keyword":"bonds investment","matchType":"EXACT","campaign":"WP - All Non-Government Bonds - High Intent","adGroup":"Generic Bonds","clicks":17,"impressions":278,"costMicros":63380405,"conversions":2,"averageCpc":3728259.117647059,"searchImpressionShare":0.0999},
  {"keyword":"australian fixed income","matchType":"EXACT","campaign":"WP - Fixed Income/Investments - QLD","adGroup":"Fixed Income (Generic)","clicks":5,"impressions":36,"costMicros":61580000,"conversions":0,"averageCpc":12316000,"searchImpressionShare":0.6451612903225806},
  {"keyword":"where to buy government bonds in australia","matchType":"EXACT","campaign":"WP - Government Bonds - E + P + B","adGroup":"Australian Government Bonds","clicks":11,"impressions":128,"costMicros":59941335,"conversions":1,"averageCpc":5449212.2727272725,"searchImpressionShare":0.18914473684210525},
  {"keyword":"retirement investing","matchType":"EXACT","campaign":"WP - Retirement","adGroup":"Retirement Informational","clicks":9,"impressions":52,"costMicros":55549175,"conversions":1,"averageCpc":6172130.555555556,"searchImpressionShare":0.3445378151260504},
  {"keyword":"fiig perth","matchType":"PHRASE","campaign":"WP - Brand","adGroup":"FIIG Securities Branded","clicks":5,"impressions":22,"costMicros":54940000,"conversions":0,"averageCpc":10988000,"searchImpressionShare":1},
  {"keyword":"government bonds australia rates","matchType":"EXACT","campaign":"WP - Government Bonds - QLD","adGroup":"Government Bond Rates","clicks":10,"impressions":30,"costMicros":54850951,"conversions":0,"averageCpc":5485095.1,"searchImpressionShare":0.5555555555555556},
  {"keyword":"investing in bonds australia","matchType":"PHRASE","campaign":"WP - Fixed Income/Investments - E + P","adGroup":"Questions/Research","clicks":12,"impressions":142,"costMicros":54207662,"conversions":1,"averageCpc":4517305.166666667,"searchImpressionShare":0.11175616835994194},
  {"keyword":"australian corporate bond market","matchType":"EXACT","campaign":"WP - All Non-Government Bonds - High Intent","adGroup":"Corporate Bonds","clicks":13,"impressions":135,"costMicros":53184662,"conversions":1.5,"averageCpc":4091127.846153846,"searchImpressionShare":0.1048313582497721},
  {"keyword":"how do i invest in bonds","matchType":"EXACT","campaign":"WP - All Non-Government Bonds - High Intent","adGroup":"Generic Bonds","clicks":10,"impressions":130,"costMicros":51888298,"conversions":0,"averageCpc":5188829.8,"searchImpressionShare":0.1123152709359606},
  {"keyword":"buy bonds","matchType":"EXACT","campaign":"WP - All Non-Government Bonds - High Intent","adGroup":"Generic Bonds","clicks":10,"impressions":128,"costMicros":50152240,"conversions":0,"averageCpc":5015224,"searchImpressionShare":0.19101123595505617},
  {"keyword":"buy australian government bonds","matchType":"EXACT","campaign":"WP - Government Bonds - QLD","adGroup":"Australian Government Bonds","clicks":18,"impressions":123,"costMicros":49587242,"conversions":0,"averageCpc":2754846.777777778,"searchImpressionShare":0.5248618784530387},
  {"keyword":"bonds online","matchType":"EXACT","campaign":"WP - All Non-Government Bonds - High Intent","adGroup":"Generic Bonds","clicks":9,"impressions":206,"costMicros":49316483,"conversions":1,"averageCpc":5479609.222222222,"searchImpressionShare":0.0999},
  {"keyword":"where to buy government bonds in australia","matchType":"EXACT","campaign":"WP - Government Bonds - QLD","adGroup":"Australian Government Bonds","clicks":6,"impressions":25,"costMicros":47116956,"conversions":0,"averageCpc":7852826,"searchImpressionShare":0.38461538461538464},
  {"keyword":"good investment","matchType":"EXACT","campaign":"WP - Fixed Income/Investments - E + P","adGroup":"Fixed Income (Generic)","clicks":7,"impressions":37,"costMicros":45856871,"conversions":0,"averageCpc":6550981.571428572,"searchImpressionShare":0.0999},
  {"keyword":"investing in government bonds","matchType":"EXACT","campaign":"WP - Government Bonds - E + P + B","adGroup":"Government Bonds (Generic)","clicks":9,"impressions":49,"costMicros":44884633,"conversions":0,"averageCpc":4987181.444444444,"searchImpressionShare":0.2214765100671141},
  {"keyword":"term investments australia","matchType":"PHRASE","campaign":"WP - Fixed Income/Investments - E + P","adGroup":"Fixed Income (Generic)","clicks":9,"impressions":124,"costMicros":44821278,"conversions":2,"averageCpc":4980142,"searchImpressionShare":0.10441334768568353},
  {"keyword":"how to invest in government bonds","matchType":"EXACT","campaign":"WP - Government Bonds - E + P + B","adGroup":"Government Bonds (Generic)","clicks":9,"impressions":137,"costMicros":44548121,"conversions":0,"averageCpc":4949791.222222222,"searchImpressionShare":0.14285714285714285},
  {"keyword":"are bonds a good investment","matchType":"EXACT","campaign":"WP - All Non-Government Bonds - High Intent","adGroup":"Generic Bonds","clicks":11,"impressions":234,"costMicros":43980014,"conversions":2,"averageCpc":3998183.090909091,"searchImpressionShare":0.0999},
  {"keyword":"transition to retirement","matchType":"EXACT","campaign":"WP - Retirement","adGroup":"Retirement Informational","clicks":5,"impressions":170,"costMicros":43683460,"conversions":1,"averageCpc":8736692,"searchImpressionShare":0.1285140562248996},
  {"keyword":"how much do government bonds pay","matchType":"EXACT","campaign":"WP - Government Bonds - E + P + B","adGroup":"Government Bonds (Generic)","clicks":13,"impressions":124,"costMicros":41164410,"conversions":0,"averageCpc":3166493.076923077,"searchImpressionShare":0.1847246891651865},
  {"keyword":"government bonds to buy","matchType":"EXACT","campaign":"WP - Government Bonds - E + P + B","adGroup":"Government Bonds (Generic)","clicks":8,"impressions":96,"costMicros":40297244,"conversions":0.5,"averageCpc":5037155.5,"searchImpressionShare":0.14389799635701275},
  {"keyword":"invest in australian government bonds","matchType":"EXACT","campaign":"WP - Government Bonds - E + P + B","adGroup":"Australian Government Bonds","clicks":12,"impressions":124,"costMicros":34020369,"conversions":1,"averageCpc":2835030.75,"searchImpressionShare":0.1216867469879518},
  {"keyword":"australian investment bonds","matchType":"EXACT","campaign":"WP - All Non-Government Bonds - High Intent","adGroup":"Australian Bonds","clicks":8,"impressions":200,"costMicros":31340529,"conversions":0,"averageCpc":3917566.125,"searchImpressionShare":0.11795204147764096},
  {"keyword":"investment trusts","matchType":"PHRASE","campaign":"WP - Fixed Income/Investments - E + P","adGroup":"Fixed Income (Generic)","clicks":1,"impressions":53,"costMicros":30411438,"conversions":1,"averageCpc":30411438,"searchImpressionShare":0.0999},
  {"keyword":"fixed interest australia","matchType":"PHRASE","campaign":"WP - Fixed Income/Investments - E + P","adGroup":"Fixed Income (Generic)","clicks":9,"impressions":68,"costMicros":29267222,"conversions":0,"averageCpc":3251913.5555555555,"searchImpressionShare":0.1417910447761194},
  {"keyword":"australia bond","matchType":"EXACT","campaign":"WP - All Non-Government Bonds - High Intent","adGroup":"Australian Bonds","clicks":5,"impressions":41,"costMicros":23699106,"conversions":0,"averageCpc":4739821.2,"searchImpressionShare":0.11538461538461539},
  {"keyword":"how to invest in fixed income bonds","matchType":"PHRASE","campaign":"WP - Fixed Income/Investments - E + P","adGroup":"Questions/Research","clicks":6,"impressions":31,"costMicros":23150221,"conversions":2,"averageCpc":3858370.1666666665,"searchImpressionShare":0.1810344827586207},
  {"keyword":"are australian government bonds a good investment","matchType":"PHRASE","campaign":"WP - Government Bonds - QLD","adGroup":"Australian Government Bonds","clicks":5,"impressions":29,"costMicros":22557097,"conversions":1,"averageCpc":4511419.4,"searchImpressionShare":0.3026315789473684},
  {"keyword":"bonds investment","matchType":"EXACT","campaign":"WP - Fixed Income/Investments - E + P","adGroup":"Fixed Income (Generic)","clicks":6,"impressions":33,"costMicros":21521502,"conversions":0.797766,"averageCpc":3586917,"searchImpressionShare":0.13368983957219252},
  {"keyword":"fixed income","matchType":"EXACT","campaign":"WP - Fixed Income/Investments - E + P","adGroup":"Fixed Income (Generic)","clicks":3,"impressions":63,"costMicros":18378482,"conversions":0,"averageCpc":6126160.666666667,"searchImpressionShare":0.14454277286135694},
  {"keyword":"fixed income","matchType":"EXACT","campaign":"WP - Fixed Income/Investments - QLD","adGroup":"Fixed Income (Generic)","clicks":1,"impressions":24,"costMicros":17570000,"conversions":0,"averageCpc":17570000,"searchImpressionShare":0.6071428571428571},
  {"keyword":"investing in government bonds australia","matchType":"EXACT","campaign":"WP - Government Bonds - QLD","adGroup":"Australian Government Bonds","clicks":4,"impressions":9,"costMicros":15960094,"conversions":0,"averageCpc":3990023.5,"searchImpressionShare":0.6363636363636364},
  {"keyword":"passive income australia","matchType":"EXACT","campaign":"WP - Fixed Income/Investments - E + P","adGroup":"Passive Income","clicks":3,"impressions":26,"costMicros":15477580,"conversions":1,"averageCpc":5159193.333333333,"searchImpressionShare":0.0999},
  {"keyword":"investment bonds australia","matchType":"PHRASE","campaign":"WP - All Non-Government Bonds - High Intent","adGroup":"Australian Bonds","clicks":4,"impressions":74,"costMicros":15326249,"conversions":0,"averageCpc":3831562.25,"searchImpressionShare":0.12551440329218108},
  {"keyword":"bond etfs australia","matchType":"EXACT","campaign":"WP - All Non-Government Bonds - High Intent","adGroup":"Australian Bonds","clicks":4,"impressions":67,"costMicros":15205361,"conversions":0,"averageCpc":3801340.25,"searchImpressionShare":0.10687022900763359},
  {"keyword":"is fixed interest a good investment","matchType":"PHRASE","campaign":"WP - Fixed Income/Investments - E + P","adGroup":"Questions/Research","clicks":4,"impressions":13,"costMicros":13812869,"conversions":0,"averageCpc":3453217.25,"searchImpressionShare":0.3793103448275862},
  {"keyword":"retirement planning australia","matchType":"EXACT","campaign":"WP - Retirement","adGroup":"Retirement Informational","clicks":2,"impressions":24,"costMicros":13504038,"conversions":0,"averageCpc":6752019,"searchImpressionShare":0.3088235294117647},
  {"keyword":"bond market australia","matchType":"EXACT","campaign":"WP - All Non-Government Bonds - High Intent","adGroup":"Australian Bonds","clicks":4,"impressions":19,"costMicros":13370032,"conversions":0,"averageCpc":3342508,"searchImpressionShare":0.20512820512820512},
  {"keyword":"what are fixed income bonds","matchType":"PHRASE","campaign":"WP - Fixed Income/Investments - E + P","adGroup":"Questions/Research","clicks":3,"impressions":17,"costMicros":13355842,"conversions":0,"averageCpc":4451947.333333333,"searchImpressionShare":0.4583333333333333}
]
